[
  {
    "company_cnpj": "26888098000906",
    "company_nome": "VOLPE FILIAL 09",
    "category": "Despesas Operacionais",
    "date": "2025-01-01",
    "created_at": "2025-11-17T01:52:22.940Z",
    "kind": "out",
    "amount": 474745.08
  },
  {
    "company_cnpj": "26888098000906",
    "company_nome": "VOLPE FILIAL 09",
    "category": "Receitas Financeiras",
    "date": "2025-01-01",
    "created_at": "2025-11-17T01:52:22.940Z",
    "kind": "out",
    "amount": 77794.32
  },
  {
    "company_cnpj": "26888098000906",
    "company_nome": "VOLPE FILIAL 09",
    "category": "Outras Receitas/Despesas",
    "date": "2024-12-01",
    "created_at": "2025-11-17T01:52:22.940Z",
    "kind": "out",
    "amount": 962.35
  },
  {
    "company_cnpj": "26888098000906",
    "company_nome": "VOLPE FILIAL 09",
    "category": "Despesas Financeiras",
    "date": "2025-01-01",
    "created_at": "2025-11-17T01:52:22.940Z",
    "kind": "out",
    "amount": 619.34
  },
  {
    "company_cnpj": "26888098000906",
    "company_nome": "VOLPE FILIAL 09",
    "category": "Outras Receitas/Despesas",
    "date": "2025-01-01",
    "created_at": "2025-11-17T01:52:22.940Z",
    "kind": "in",
    "amount": 2683.36
  },
  {
    "company_cnpj": "26888098000906",
    "company_nome": "VOLPE FILIAL 09",
    "category": "Outras Receitas/Despesas",
    "date": "2025-01-01",
    "created_at": "2025-11-17T01:52:22.940Z",
    "kind": "out",
    "amount": 3014.26
  },
  {
    "company_cnpj": "26888098000906",
    "company_nome": "VOLPE FILIAL 09",
    "category": "Despesas Administrativas",
    "date": "2025-01-01",
    "created_at": "2025-11-17T01:52:22.940Z",
    "kind": "out",
    "amount": 5516.58
  },
  {
    "company_cnpj": "26888098000906",
    "company_nome": "VOLPE FILIAL 09",
    "category": "Despesas Com Pessoal",
    "date": "2025-01-01",
    "created_at": "2025-11-17T01:52:22.940Z",
    "kind": "out",
    "amount": 13237.36
  },
  {
    "company_cnpj": "26888098000906",
    "company_nome": "VOLPE FILIAL 09",
    "category": "Despesas Administrativas",
    "date": "2025-02-01",
    "created_at": "2025-11-17T01:52:22.940Z",
    "kind": "out",
    "amount": 5777.42
  },
  {
    "company_cnpj": "26888098000906",
    "company_nome": "VOLPE FILIAL 09",
    "category": "Despesas Financeiras",
    "date": "2025-02-01",
    "created_at": "2025-11-17T01:52:22.940Z",
    "kind": "out",
    "amount": 591.27
  },
  {
    "company_cnpj": "26888098000906",
    "company_nome": "VOLPE FILIAL 09",
    "category": "Despesas Operacionais",
    "date": "2025-02-01",
    "created_at": "2025-11-17T01:52:22.940Z",
    "kind": "out",
    "amount": 442556.91
  },
  {
    "company_cnpj": "26888098000906",
    "company_nome": "VOLPE FILIAL 09",
    "category": "Outras Receitas/Despesas",
    "date": "2025-02-01",
    "created_at": "2025-11-17T01:52:22.940Z",
    "kind": "in",
    "amount": 0.28
  },
  {
    "company_cnpj": "26888098000906",
    "company_nome": "VOLPE FILIAL 09",
    "category": "Outras Receitas/Despesas",
    "date": "2025-02-01",
    "created_at": "2025-11-17T01:52:22.940Z",
    "kind": "out",
    "amount": 3921.37
  },
  {
    "company_cnpj": "26888098000906",
    "company_nome": "VOLPE FILIAL 09",
    "category": "Despesas Com Pessoal",
    "date": "2025-02-01",
    "created_at": "2025-11-17T01:52:22.940Z",
    "kind": "out",
    "amount": 14249.21
  },
  {
    "company_cnpj": "26888098000906",
    "company_nome": "VOLPE FILIAL 09",
    "category": "Deduções de Receitas",
    "date": "2025-02-01",
    "created_at": "2025-11-17T01:52:22.940Z",
    "kind": "in",
    "amount": 103838.27
  },
  {
    "company_cnpj": "26888098000906",
    "company_nome": "VOLPE FILIAL 09",
    "category": "Deduções de Receitas",
    "date": "2025-02-01",
    "created_at": "2025-11-17T01:52:22.940Z",
    "kind": "out",
    "amount": 163.64
  },
  {
    "company_cnpj": "26888098000906",
    "company_nome": "VOLPE FILIAL 09",
    "category": "Despesas Administrativas",
    "date": "2025-03-01",
    "created_at": "2025-11-17T01:52:22.940Z",
    "kind": "out",
    "amount": 5957.11
  },
  {
    "company_cnpj": "26888098000906",
    "company_nome": "VOLPE FILIAL 09",
    "category": "Despesas Com Pessoal",
    "date": "2025-03-01",
    "created_at": "2025-11-17T01:52:22.940Z",
    "kind": "out",
    "amount": 22445.76
  },
  {
    "company_cnpj": "26888098000906",
    "company_nome": "VOLPE FILIAL 09",
    "category": "Despesas Operacionais",
    "date": "2025-03-01",
    "created_at": "2025-11-17T01:52:22.940Z",
    "kind": "out",
    "amount": 484581.62
  },
  {
    "company_cnpj": "26888098000906",
    "company_nome": "VOLPE FILIAL 09",
    "category": "Despesas Financeiras",
    "date": "2025-03-01",
    "created_at": "2025-11-17T01:52:22.940Z",
    "kind": "out",
    "amount": 950.04
  },
  {
    "company_cnpj": "26888098000906",
    "company_nome": "VOLPE FILIAL 09",
    "category": "Outras Receitas/Despesas",
    "date": "2025-03-01",
    "created_at": "2025-11-17T01:52:22.940Z",
    "kind": "in",
    "amount": 0.01
  },
  {
    "company_cnpj": "26888098000906",
    "company_nome": "VOLPE FILIAL 09",
    "category": "Outras Receitas/Despesas",
    "date": "2025-03-01",
    "created_at": "2025-11-17T01:52:22.940Z",
    "kind": "out",
    "amount": 3078.79
  },
  {
    "company_cnpj": "26888098000906",
    "company_nome": "VOLPE FILIAL 09",
    "category": "Deduções de Receitas",
    "date": "2025-03-01",
    "created_at": "2025-11-17T01:52:22.940Z",
    "kind": "in",
    "amount": 136351.8
  },
  {
    "company_cnpj": "26888098000906",
    "company_nome": "VOLPE FILIAL 09",
    "category": "Deduções de Receitas",
    "date": "2025-03-01",
    "created_at": "2025-11-17T01:52:22.940Z",
    "kind": "out",
    "amount": 159.8
  },
  {
    "company_cnpj": "26888098000906",
    "company_nome": "VOLPE FILIAL 09",
    "category": "Despesas Com Pessoal",
    "date": "2025-04-01",
    "created_at": "2025-11-17T01:52:22.940Z",
    "kind": "out",
    "amount": 23510.83
  },
  {
    "company_cnpj": "26888098000906",
    "company_nome": "VOLPE FILIAL 09",
    "category": "Despesas Administrativas",
    "date": "2025-04-01",
    "created_at": "2025-11-17T01:52:22.940Z",
    "kind": "out",
    "amount": 5698.25
  },
  {
    "company_cnpj": "26888098000906",
    "company_nome": "VOLPE FILIAL 09",
    "category": "Despesas Operacionais",
    "date": "2025-04-01",
    "created_at": "2025-11-17T01:52:22.940Z",
    "kind": "out",
    "amount": 501225.04
  },
  {
    "company_cnpj": "26888098000906",
    "company_nome": "VOLPE FILIAL 09",
    "category": "Outras Receitas/Despesas",
    "date": "2025-04-01",
    "created_at": "2025-11-17T01:52:22.940Z",
    "kind": "out",
    "amount": 3215.84
  },
  {
    "company_cnpj": "26888098000906",
    "company_nome": "VOLPE FILIAL 09",
    "category": "Despesas Financeiras",
    "date": "2025-04-01",
    "created_at": "2025-11-17T01:52:22.940Z",
    "kind": "out",
    "amount": 280
  },
  {
    "company_cnpj": "26888098000906",
    "company_nome": "VOLPE FILIAL 09",
    "category": "Deduções de Receitas",
    "date": "2025-04-01",
    "created_at": "2025-11-17T01:52:22.940Z",
    "kind": "in",
    "amount": 121574.8
  },
  {
    "company_cnpj": "26888098000906",
    "company_nome": "VOLPE FILIAL 09",
    "category": "Deduções de Receitas",
    "date": "2025-04-01",
    "created_at": "2025-11-17T01:52:22.940Z",
    "kind": "out",
    "amount": 521.1
  },
  {
    "company_cnpj": "26888098000906",
    "company_nome": "VOLPE FILIAL 09",
    "category": "Despesas Operacionais",
    "date": "2025-05-01",
    "created_at": "2025-11-17T01:52:22.940Z",
    "kind": "out",
    "amount": 502079.12
  },
  {
    "company_cnpj": "26888098000906",
    "company_nome": "VOLPE FILIAL 09",
    "category": "Despesas Administrativas",
    "date": "2025-05-01",
    "created_at": "2025-11-17T01:52:22.940Z",
    "kind": "out",
    "amount": 5896.06
  },
  {
    "company_cnpj": "26888098000906",
    "company_nome": "VOLPE FILIAL 09",
    "category": "Despesas Financeiras",
    "date": "2025-05-01",
    "created_at": "2025-11-17T01:52:22.940Z",
    "kind": "out",
    "amount": 700.69
  },
  {
    "company_cnpj": "26888098000906",
    "company_nome": "VOLPE FILIAL 09",
    "category": "Outras Receitas/Despesas",
    "date": "2025-05-01",
    "created_at": "2025-11-17T01:52:22.940Z",
    "kind": "in",
    "amount": 1150
  },
  {
    "company_cnpj": "26888098000906",
    "company_nome": "VOLPE FILIAL 09",
    "category": "Outras Receitas/Despesas",
    "date": "2025-05-01",
    "created_at": "2025-11-17T01:52:22.940Z",
    "kind": "out",
    "amount": 3623.98
  },
  {
    "company_cnpj": "26888098000906",
    "company_nome": "VOLPE FILIAL 09",
    "category": "Despesas Com Pessoal",
    "date": "2025-05-01",
    "created_at": "2025-11-17T01:52:22.940Z",
    "kind": "out",
    "amount": 20879.7
  },
  {
    "company_cnpj": "26888098000906",
    "company_nome": "VOLPE FILIAL 09",
    "category": "Despesas Administrativas",
    "date": "2025-06-01",
    "created_at": "2025-11-17T01:52:22.940Z",
    "kind": "out",
    "amount": 5995.41
  },
  {
    "company_cnpj": "26888098000906",
    "company_nome": "VOLPE FILIAL 09",
    "category": "Despesas Operacionais",
    "date": "2025-06-01",
    "created_at": "2025-11-17T01:52:22.940Z",
    "kind": "out",
    "amount": 407500.51
  },
  {
    "company_cnpj": "26888098000906",
    "company_nome": "VOLPE FILIAL 09",
    "category": "Despesas Financeiras",
    "date": "2025-06-01",
    "created_at": "2025-11-17T01:52:22.940Z",
    "kind": "out",
    "amount": 983.07
  },
  {
    "company_cnpj": "26888098000906",
    "company_nome": "VOLPE FILIAL 09",
    "category": "Outras Receitas/Despesas",
    "date": "2025-06-01",
    "created_at": "2025-11-17T01:52:22.940Z",
    "kind": "in",
    "amount": 1719.64
  },
  {
    "company_cnpj": "26888098000906",
    "company_nome": "VOLPE FILIAL 09",
    "category": "Outras Receitas/Despesas",
    "date": "2025-06-01",
    "created_at": "2025-11-17T01:52:22.940Z",
    "kind": "out",
    "amount": 3246.98
  },
  {
    "company_cnpj": "26888098000906",
    "company_nome": "VOLPE FILIAL 09",
    "category": "Despesas Com Pessoal",
    "date": "2025-06-01",
    "created_at": "2025-11-17T01:52:22.940Z",
    "kind": "out",
    "amount": 24076.27
  },
  {
    "company_cnpj": "26888098000906",
    "company_nome": "VOLPE FILIAL 09",
    "category": "Despesas Administrativas",
    "date": "2025-07-01",
    "created_at": "2025-11-17T01:52:22.940Z",
    "kind": "out",
    "amount": 7045.98
  },
  {
    "company_cnpj": "26888098000906",
    "company_nome": "VOLPE FILIAL 09",
    "category": "Despesas Operacionais",
    "date": "2025-07-01",
    "created_at": "2025-11-17T01:52:22.940Z",
    "kind": "out",
    "amount": 372409.17
  },
  {
    "company_cnpj": "26888098000906",
    "company_nome": "VOLPE FILIAL 09",
    "category": "Despesas Financeiras",
    "date": "2025-07-01",
    "created_at": "2025-11-17T01:52:22.940Z",
    "kind": "out",
    "amount": 1086.61
  },
  {
    "company_cnpj": "26888098000906",
    "company_nome": "VOLPE FILIAL 09",
    "category": "Despesas Com Pessoal",
    "date": "2025-07-01",
    "created_at": "2025-11-17T01:52:22.940Z",
    "kind": "out",
    "amount": 32878.04
  },
  {
    "company_cnpj": "26888098000906",
    "company_nome": "VOLPE FILIAL 09",
    "category": "Outras Receitas/Despesas",
    "date": "2025-07-01",
    "created_at": "2025-11-17T01:52:22.940Z",
    "kind": "in",
    "amount": 776.77
  },
  {
    "company_cnpj": "26888098000906",
    "company_nome": "VOLPE FILIAL 09",
    "category": "Outras Receitas/Despesas",
    "date": "2025-07-01",
    "created_at": "2025-11-17T01:52:22.940Z",
    "kind": "out",
    "amount": 2843.61
  },
  {
    "company_cnpj": "26888098000906",
    "company_nome": "VOLPE FILIAL 09",
    "category": "Receitas Financeiras",
    "date": "2025-07-01",
    "created_at": "2025-11-17T01:52:22.940Z",
    "kind": "out",
    "amount": 35487.96
  },
  {
    "company_cnpj": "26888098000906",
    "company_nome": "VOLPE FILIAL 09",
    "category": "Impostos Sobre o Faturamento",
    "date": "2025-07-01",
    "created_at": "2025-11-17T01:52:22.940Z",
    "kind": "out",
    "amount": 562.41
  },
  {
    "company_cnpj": "26888098000906",
    "company_nome": "VOLPE FILIAL 09",
    "category": "Despesas Administrativas",
    "date": "2025-08-01",
    "created_at": "2025-11-17T01:52:22.940Z",
    "kind": "out",
    "amount": 5691.95
  },
  {
    "company_cnpj": "26888098000906",
    "company_nome": "VOLPE FILIAL 09",
    "category": "Despesas Operacionais",
    "date": "2025-08-01",
    "created_at": "2025-11-17T01:52:22.940Z",
    "kind": "out",
    "amount": 431330.7
  },
  {
    "company_cnpj": "26888098000906",
    "company_nome": "VOLPE FILIAL 09",
    "category": "Despesas Financeiras",
    "date": "2025-08-01",
    "created_at": "2025-11-17T01:52:22.940Z",
    "kind": "out",
    "amount": 484.25
  },
  {
    "company_cnpj": "26888098000906",
    "company_nome": "VOLPE FILIAL 09",
    "category": "Outras Receitas/Despesas",
    "date": "2025-08-01",
    "created_at": "2025-11-17T01:52:22.940Z",
    "kind": "out",
    "amount": 3056.74
  },
  {
    "company_cnpj": "26888098000906",
    "company_nome": "VOLPE FILIAL 09",
    "category": "Despesas Com Pessoal",
    "date": "2025-08-01",
    "created_at": "2025-11-17T01:52:22.940Z",
    "kind": "out",
    "amount": 23845.39
  },
  {
    "company_cnpj": "26888098000906",
    "company_nome": "VOLPE FILIAL 09",
    "category": "Despesas Administrativas",
    "date": "2025-09-01",
    "created_at": "2025-11-17T01:52:22.940Z",
    "kind": "out",
    "amount": 5671.05
  },
  {
    "company_cnpj": "26888098000906",
    "company_nome": "VOLPE FILIAL 09",
    "category": "Despesas Operacionais",
    "date": "2025-09-01",
    "created_at": "2025-11-17T01:52:22.940Z",
    "kind": "out",
    "amount": 369650.14
  },
  {
    "company_cnpj": "26888098000906",
    "company_nome": "VOLPE FILIAL 09",
    "category": "Despesas Financeiras",
    "date": "2025-09-01",
    "created_at": "2025-11-17T01:52:22.940Z",
    "kind": "out",
    "amount": 455.67
  },
  {
    "company_cnpj": "26888098000906",
    "company_nome": "VOLPE FILIAL 09",
    "category": "Outras Receitas/Despesas",
    "date": "2025-09-01",
    "created_at": "2025-11-17T01:52:22.940Z",
    "kind": "out",
    "amount": 3397.12
  },
  {
    "company_cnpj": "26888098000906",
    "company_nome": "VOLPE FILIAL 09",
    "category": "Despesas Com Pessoal",
    "date": "2025-09-01",
    "created_at": "2025-11-17T01:52:22.940Z",
    "kind": "out",
    "amount": 26758.07
  },
  {
    "company_cnpj": "26888098000906",
    "company_nome": "VOLPE FILIAL 09",
    "category": "Deduções de Receitas",
    "date": "2025-09-01",
    "created_at": "2025-11-17T01:52:22.940Z",
    "kind": "in",
    "amount": 75741.19
  },
  {
    "company_cnpj": "26888098000906",
    "company_nome": "VOLPE FILIAL 09",
    "category": "Deduções de Receitas",
    "date": "2025-09-01",
    "created_at": "2025-11-17T01:52:22.940Z",
    "kind": "out",
    "amount": 393.9
  },
  {
    "company_cnpj": "26888098000906",
    "company_nome": "VOLPE FILIAL 09",
    "category": "Despesas Administrativas",
    "date": "2025-10-01",
    "created_at": "2025-11-17T01:52:22.940Z",
    "kind": "out",
    "amount": 5665.96
  },
  {
    "company_cnpj": "26888098000906",
    "company_nome": "VOLPE FILIAL 09",
    "category": "Despesas Operacionais",
    "date": "2025-10-01",
    "created_at": "2025-11-17T01:52:22.940Z",
    "kind": "out",
    "amount": 316871.24
  },
  {
    "company_cnpj": "26888098000906",
    "company_nome": "VOLPE FILIAL 09",
    "category": "Despesas Financeiras",
    "date": "2025-10-01",
    "created_at": "2025-11-17T01:52:22.940Z",
    "kind": "out",
    "amount": 215.4
  },
  {
    "company_cnpj": "26888098000906",
    "company_nome": "VOLPE FILIAL 09",
    "category": "Outras Receitas/Despesas",
    "date": "2025-10-01",
    "created_at": "2025-11-17T01:52:22.940Z",
    "kind": "out",
    "amount": 2404.63
  },
  {
    "company_cnpj": "26888098000906",
    "company_nome": "VOLPE FILIAL 09",
    "category": "Despesas Com Pessoal",
    "date": "2025-10-01",
    "created_at": "2025-11-17T01:52:22.940Z",
    "kind": "out",
    "amount": 30391.14
  },
  {
    "company_cnpj": "26888098000906",
    "company_nome": "VOLPE FILIAL 09",
    "category": "Despesas Administrativas",
    "date": "2025-11-01",
    "created_at": "2025-11-17T01:52:22.940Z",
    "kind": "out",
    "amount": 1129
  },
  {
    "company_cnpj": "26888098000906",
    "company_nome": "VOLPE FILIAL 09",
    "category": "Despesas Com Pessoal",
    "date": "2025-11-01",
    "created_at": "2025-11-17T01:52:22.940Z",
    "kind": "out",
    "amount": 1074.6
  },
  {
    "company_cnpj": "26888098000906",
    "company_nome": "VOLPE FILIAL 09",
    "category": "Deduções de Receitas",
    "date": "2025-06-01",
    "created_at": "2025-11-17T01:52:22.940Z",
    "kind": "in",
    "amount": 97796.28
  },
  {
    "company_cnpj": "26888098000906",
    "company_nome": "VOLPE FILIAL 09",
    "category": "Deduções de Receitas",
    "date": "2025-06-01",
    "created_at": "2025-11-17T01:52:22.940Z",
    "kind": "out",
    "amount": 89.9
  },
  {
    "company_cnpj": "26888098000906",
    "company_nome": "VOLPE FILIAL 09",
    "category": "Receitas Operacionais",
    "date": "2025-01-01",
    "created_at": "2025-11-17T01:52:22.940Z",
    "kind": "in",
    "amount": 488126.4
  },
  {
    "company_cnpj": "26888098000906",
    "company_nome": "VOLPE FILIAL 09",
    "category": "Receitas Operacionais",
    "date": "2025-02-01",
    "created_at": "2025-11-17T01:52:22.940Z",
    "kind": "in",
    "amount": 502292.59
  },
  {
    "company_cnpj": "26888098000906",
    "company_nome": "VOLPE FILIAL 09",
    "category": "Receitas Operacionais",
    "date": "2025-03-01",
    "created_at": "2025-11-17T01:52:22.940Z",
    "kind": "in",
    "amount": 656607.1
  },
  {
    "company_cnpj": "26888098000906",
    "company_nome": "VOLPE FILIAL 09",
    "category": "Receitas Operacionais",
    "date": "2025-04-01",
    "created_at": "2025-11-17T01:52:22.940Z",
    "kind": "in",
    "amount": 588963.41
  },
  {
    "company_cnpj": "26888098000906",
    "company_nome": "VOLPE FILIAL 09",
    "category": "Receitas Operacionais",
    "date": "2025-05-01",
    "created_at": "2025-11-17T01:52:22.940Z",
    "kind": "in",
    "amount": 580431.13
  },
  {
    "company_cnpj": "26888098000906",
    "company_nome": "VOLPE FILIAL 09",
    "category": "Receitas Operacionais",
    "date": "2025-06-01",
    "created_at": "2025-11-17T01:52:22.940Z",
    "kind": "in",
    "amount": 521160.37
  },
  {
    "company_cnpj": "26888098000906",
    "company_nome": "VOLPE FILIAL 09",
    "category": "Receitas Operacionais",
    "date": "2025-07-01",
    "created_at": "2025-11-17T01:52:22.940Z",
    "kind": "in",
    "amount": 500322.8
  },
  {
    "company_cnpj": "26888098000906",
    "company_nome": "VOLPE FILIAL 09",
    "category": "Receitas Operacionais",
    "date": "2025-08-01",
    "created_at": "2025-11-17T01:52:22.940Z",
    "kind": "in",
    "amount": 525205.95
  },
  {
    "company_cnpj": "26888098000906",
    "company_nome": "VOLPE FILIAL 09",
    "category": "Receitas Operacionais",
    "date": "2025-09-01",
    "created_at": "2025-11-17T01:52:22.940Z",
    "kind": "in",
    "amount": 475808.69
  },
  {
    "company_cnpj": "26888098000906",
    "company_nome": "VOLPE FILIAL 09",
    "category": "Receitas Operacionais",
    "date": "2025-10-01",
    "created_at": "2025-11-17T01:52:22.940Z",
    "kind": "in",
    "amount": 419035.82
  },
  {
    "company_cnpj": "26888098000906",
    "company_nome": "VOLPE FILIAL 09",
    "category": "Deduções de Receitas",
    "date": "2025-01-01",
    "created_at": "2025-11-17T01:52:22.940Z",
    "kind": "in",
    "amount": 54952.68
  },
  {
    "company_cnpj": "26888098000906",
    "company_nome": "VOLPE FILIAL 09",
    "category": "Deduções de Receitas",
    "date": "2025-01-01",
    "created_at": "2025-11-17T01:52:22.940Z",
    "kind": "out",
    "amount": 79.9
  },
  {
    "company_cnpj": "26888098000906",
    "company_nome": "VOLPE FILIAL 09",
    "category": "Deduções de Receitas",
    "date": "2025-05-01",
    "created_at": "2025-11-17T01:52:22.940Z",
    "kind": "in",
    "amount": 105134.71
  },
  {
    "company_cnpj": "26888098000906",
    "company_nome": "VOLPE FILIAL 09",
    "category": "Deduções de Receitas",
    "date": "2025-05-01",
    "created_at": "2025-11-17T01:52:22.940Z",
    "kind": "out",
    "amount": 79.9
  },
  {
    "company_cnpj": "26888098000906",
    "company_nome": "VOLPE FILIAL 09",
    "category": "Deduções de Receitas",
    "date": "2025-08-01",
    "created_at": "2025-11-17T01:52:22.940Z",
    "kind": "in",
    "amount": 80273.54
  },
  {
    "company_cnpj": "26888098000906",
    "company_nome": "VOLPE FILIAL 09",
    "category": "Deduções de Receitas",
    "date": "2025-08-01",
    "created_at": "2025-11-17T01:52:22.940Z",
    "kind": "out",
    "amount": 125.7
  },
  {
    "company_cnpj": "26888098000906",
    "company_nome": "VOLPE FILIAL 09",
    "category": "Deduções de Receitas",
    "date": "2025-10-01",
    "created_at": "2025-11-17T01:52:22.940Z",
    "kind": "in",
    "amount": 73048.32
  },
  {
    "company_cnpj": "26888098000906",
    "company_nome": "VOLPE FILIAL 09",
    "category": "Deduções de Receitas",
    "date": "2025-10-01",
    "created_at": "2025-11-17T01:52:22.940Z",
    "kind": "out",
    "amount": 129.9
  },
  {
    "company_cnpj": "26888098000906",
    "company_nome": "VOLPE FILIAL 09",
    "category": "Deduções de Receitas",
    "date": "2025-07-01",
    "created_at": "2025-11-17T01:52:22.940Z",
    "kind": "in",
    "amount": 89064.8
  },
  {
    "company_cnpj": "26888098000906",
    "company_nome": "VOLPE FILIAL 09",
    "category": "Receitas Operacionais",
    "date": "2025-11-01",
    "created_at": "2025-11-17T01:52:22.940Z",
    "kind": "in",
    "amount": 31859.43
  },
  {
    "company_cnpj": "26888098000906",
    "company_nome": "VOLPE FILIAL 09",
    "category": "Deduções de Receitas",
    "date": "2025-11-01",
    "created_at": "2025-11-17T01:52:22.940Z",
    "kind": "in",
    "amount": 31859.43
  }
]